README.txt
setup.cfg
setup.py
tapblue/__init__.py
tapblue/blue.py
tapblue.egg-info/PKG-INFO
tapblue.egg-info/SOURCES.txt
tapblue.egg-info/dependency_links.txt
tapblue.egg-info/not-zip-safe
tapblue.egg-info/requires.txt
tapblue.egg-info/top_level.txt