Metadata-Version: 1.0
Name: tapblue
Version: 0.2
Summary: The button for hackers and techies
Home-page: https://github.com/nchafni/tapblue
Author: Nezare Chafni
Author-email: nchafni@tap.blue
License: MIT
Platform: UNKNOWN
